{"name":"Spruance (8350)","region":"Northeast","address":"6401 Horrocks St, Philadelphia, PA  19149","fci":"0.6228","status":" Open","level":" Elementary School","demographics":[{"name":"American Indian / Alaska Nativ","count":"2","percentage":"0%"},{"name":"Asian","count":"217","percentage":"16%"},{"name":"Black / African American","count":"545","percentage":"41%"},{"name":"Hispanic / Latino","count":"316","percentage":"24%"},{"name":"Multi Racial / Other","count":"104","percentage":"8%"},{"name":"White","count":"155","percentage":"12%"}],"Status":"Open","Start Date":"7/1/1949","Level":"Elementary School","Type":"Neighborhood","Admit Type":"Neighborhood","Managed":"District","Principal":"Betty G. Klear","Reading K-3 or Better":"55%","Adv/Prof Math (E-M)":"60","Adv/Prof Reading (E-M)":"55","AGI Math":"-2.7","AGI Reading":"2.4","On-Track/Time Grad":"","Graduation Rate":"","Grad College (yr 1)":"","Adv/Prof Math (HS)":"","Adv/Prof Reading (HS)":"","Avg Daily Attendance":"95%","10+ Absences":"33%","At Least 1 OSS":"5%","VI Per 100":"0.84","Persistently Dangerous":"No","Neighborhood (SDP) In":"1257","Neighborhood (SDP) Out":"90","Neighborhood (Ren)":"7","Neighborhood (Charter)":"0","Charter":"194","CTE":"0","Special Admission":"15","Citywide Admission":"0","Military Academy":"0","Other":"4","Condition Assessment Cost":"$23,253,382","Replacement Cost":"$33,911,476","Facilities Condition Index":"0.6228","No. of Floors":"2","S.F. (Building)":"102,143","S.F. (Site)":"280,857 6.4 acs","S.F. (Footprint)":"63,441","Capacity":"835","Year Built":"1949"}